globaleaks_ephemeral_fs/__init__.py
test_globaleaks_ephemeral_fs-0.0.2.dist-info/LICENSE
test_globaleaks_ephemeral_fs-0.0.2.dist-info/METADATA
test_globaleaks_ephemeral_fs-0.0.2.dist-info/WHEEL
test_globaleaks_ephemeral_fs-0.0.2.dist-info/top_level.txt
test_globaleaks_ephemeral_fs-0.0.2.dist-info/RECORD
