Metadata-Version: 2.1
Name: test_globaleaks_ephemeral_fs
Version: 0.0.2
Summary: An ephemeral ChaCha20-encrypted filesystem implementation using fusepy and cryptography suitable for privacy-sensitive applications, such as whistleblowing platforms. 
Author-email: Giovanni Pellerano <giovanni.pellerano@globaleaks.org>
Project-URL: Homepage, https://github.com/globaleaks/globaleaks-ephemeral-fs
Project-URL: Issues, https://github.com/globaleaks/globaleaks-ephemeral-fs/issues
Classifier: Programming Language :: Python :: 3
Classifier: License :: OSI Approved :: GNU Affero General Public License v3 or later (AGPLv3+)
Classifier: Operating System :: OS Independent
Requires-Python: >=3.8
License-File: LICENSE
